sokrato/__init__.py
sokrato/cli.py
sokrato-0.0.1.dist-info/LICENSE
sokrato-0.0.1.dist-info/METADATA
sokrato-0.0.1.dist-info/WHEEL
sokrato-0.0.1.dist-info/entry_points.txt
sokrato-0.0.1.dist-info/top_level.txt
sokrato-0.0.1.dist-info/RECORD
